ipv4helper.py
ipv4helper-0.9.1.dist-info/LICENSE
ipv4helper-0.9.1.dist-info/METADATA
ipv4helper-0.9.1.dist-info/WHEEL
ipv4helper-0.9.1.dist-info/top_level.txt
ipv4helper-0.9.1.dist-info/RECORD
