Metadata-Version: 2.1
Name: ipv4helper
Version: 0.9.1
Summary: Handle and manipulate IPv4 CIDRs in a simple fashion, including generating CIDR ranges and viewing general subnet information.
Home-page: https://github.com/bonifield/IPv4Helper
Author: James Bonifield
Author-email: bonifield.tools@gmail.com
License: UNKNOWN
Platform: UNKNOWN
Classifier: Programming Language :: Python :: 3
Classifier: License :: OSI Approved :: MIT License
Classifier: Operating System :: OS Independent
